{"cameraMode":{"drawMode":0,"name":"Shaded","section":"Shading Mode"},"sceneLighting":true,"audioPlay":false,"sceneViewState":{"m_AlwaysRefresh":false,"showFog":true,"showSkybox":true,"showFlares":true,"showImageEffects":true,"showParticleSystems":true,"showVisualEffectGraphs":true,"m_FxEnabled":true},"in2DMode":false,"pivot":{"x":25.54050636291504,"y":-0.9545345306396484,"z":24.417682647705079},"rotation":{"x":0.2323855310678482,"y":0.3904062509536743,"z":-0.10252360999584198,"w":0.8849129676818848},"size":10.0,"orthographic":false}